ocgan/__init__.py
ocgan/dataset.py
ocgan/models.py
ocgan/ocgan.py
ocgan/utils.py
ocgan-1.0.dist-info/METADATA
ocgan-1.0.dist-info/WHEEL
ocgan-1.0.dist-info/top_level.txt
ocgan-1.0.dist-info/RECORD
