Metadata-Version: 2.1
Name: ocgan
Version: 1.0
Summary: Tensorflow implementation of OCGAN
Home-page: https://github.com/nuclearboy95/Anomaly-Detection-OCGAN-tensorflow
Author: Jihun Yi
Author-email: t080205@gmail.com
License: MIT
Platform: UNKNOWN
Requires-Dist: numpy
Requires-Dist: scikit-learn
Requires-Dist: tensorflow-gpu (>=1.12.0)
Requires-Dist: matplotlib
Requires-Dist: tqdm
